dask_mpi/__init__.py
dask_mpi/_version.py
dask_mpi/cli.py
dask_mpi/exceptions.py
dask_mpi/execute.py
dask_mpi/initialize.py
dask_mpi/tests/__init__.py
dask_mpi/tests/conftest.py
dask_mpi/tests/execute_basic.py
dask_mpi/tests/execute_no_exit.py
dask_mpi/tests/initialize_basic.py
dask_mpi/tests/initialize_no_exit.py
dask_mpi/tests/test_cli.py
dask_mpi/tests/test_execute.py
dask_mpi/tests/test_initialize.py
dask_mpi-2025.10.0.dist-info/LICENSE.txt
dask_mpi-2025.10.0.dist-info/METADATA
dask_mpi-2025.10.0.dist-info/WHEEL
dask_mpi-2025.10.0.dist-info/entry_points.txt
dask_mpi-2025.10.0.dist-info/top_level.txt
dask_mpi-2025.10.0.dist-info/RECORD
