Metadata-Version: 2.1
Name: dask-mpi
Version: 2025.10.0
Summary: Deploy Dask using mpi4py
Home-page: https://github.com/dask/dask-mpi
Maintainer: Kevin Paul
Maintainer-email: kpaul@ucar.edu
License: BSD 3-Clause
Project-URL: Documentation, https://mpi.dask.org/
Project-URL: Source, https://github.com/dask/dask-mpi
Project-URL: Tracker, https://github.com/dask/dask-mpi/issues
Requires-Python: >=3.6,<3.12
License-File: LICENSE.txt
Requires-Dist: dask>=2.19
Requires-Dist: distributed>=2.19
Requires-Dist: mpi4py>=3.0.3
